{
  "project_info": {
    "project_number": "1031547381183",
    "project_id": "zoopzoop-a7e81",
    "storage_bucket": "zoopzoop-a7e81.appspot.com"
  },
  "client": [
    {
      "client_info": {
        "mobilesdk_app_id": "1:1031547381183:android:47c39cf475bdf001902d0a",
        "android_client_info": {
          "package_name": "com.psuh.zoopzoop"
        }
      },
      "oauth_client": [
        {
          "client_id": "1031547381183-bcobkts69783osv5o9ino9m6nbf26j4a.apps.googleusercontent.com",
          "client_type": 3
        }
      ],
      "api_key": [
        {
          "current_key": "AIzaSyBcLx51Y_Rwickm8Wod25BwvRNoCIY_eiU"
        }
      ],
      "services": {
        "appinvite_service": {
          "other_platform_oauth_client": [
            {
              "client_id": "1031547381183-bcobkts69783osv5o9ino9m6nbf26j4a.apps.googleusercontent.com",
              "client_type": 3
            },
            {
              "client_id": "1031547381183-je5qogbmv92in5gla0s2o7o9qn22vfoe.apps.googleusercontent.com",
              "client_type": 2,
              "ios_info": {
                "bundle_id": "com.push.zoopzoop"
              }
            }
          ]
        }
      }
    }
  ],
  "configuration_version": "1"
}